requests_oauth2client/__init__.py
requests_oauth2client/api_client.py
requests_oauth2client/auth.py
requests_oauth2client/authorization_request.py
requests_oauth2client/backchannel_authentication.py
requests_oauth2client/client.py
requests_oauth2client/client_authentication.py
requests_oauth2client/deprecated.py
requests_oauth2client/device_authorization.py
requests_oauth2client/discovery.py
requests_oauth2client/dpop.py
requests_oauth2client/enums.py
requests_oauth2client/exceptions.py
requests_oauth2client/polling.py
requests_oauth2client/py.typed
requests_oauth2client/serializers.py
requests_oauth2client/tokens.py
requests_oauth2client/utils.py
requests_oauth2client/flask/__init__.py
requests_oauth2client/flask/auth.py
requests_oauth2client/vendor_specific/__init__.py
requests_oauth2client/vendor_specific/auth0.py
requests_oauth2client/vendor_specific/ping.py
requests_oauth2client-1.8.0.dist-info/METADATA
requests_oauth2client-1.8.0.dist-info/WHEEL
requests_oauth2client-1.8.0.dist-info/licenses/LICENSE
requests_oauth2client-1.8.0.dist-info/RECORD
