Metadata-Version: 2.4
Name: requests_oauth2client
Version: 1.8.0
Summary: An OAuth2.x client based on `requests`.
Project-URL: Homepage, https://github.com/guillp/requests_oauth2client
Author-email: Guillaume Pujol <guillp.dev@pm.me>
License-Expression: Apache-2.0
License-File: LICENSE
Classifier: Development Status :: 4 - Beta
Classifier: Intended Audience :: Developers
Classifier: License :: OSI Approved :: Apache Software License
Classifier: Programming Language :: Python :: 3
Classifier: Programming Language :: Python :: 3.9
Classifier: Programming Language :: Python :: 3.10
Classifier: Programming Language :: Python :: 3.11
Classifier: Programming Language :: Python :: 3.12
Classifier: Programming Language :: Python :: 3.13
Classifier: Programming Language :: Python :: 3.14
Classifier: Topic :: Security
Requires-Python: >=3.9
Requires-Dist: attrs>=25.3.0
Requires-Dist: binapy>=0.8
Requires-Dist: furl>=2.1.4
Requires-Dist: jwskate>=0.12.2
Requires-Dist: requests>=2.32.5
